karton_misp_pusher-1.1.0-nspkg.pth
karton/misp_pusher/__init__.py
karton/misp_pusher/__main__.py
karton/misp_pusher/__version__.py
karton/misp_pusher/misp_pusher.py
karton_misp_pusher-1.1.0.dist-info/LICENSE
karton_misp_pusher-1.1.0.dist-info/METADATA
karton_misp_pusher-1.1.0.dist-info/WHEEL
karton_misp_pusher-1.1.0.dist-info/entry_points.txt
karton_misp_pusher-1.1.0.dist-info/namespace_packages.txt
karton_misp_pusher-1.1.0.dist-info/top_level.txt
karton_misp_pusher-1.1.0.dist-info/RECORD
