Metadata-Version: 2.1
Name: karton-misp-pusher
Version: 1.1.0
Summary: MISP reporter for the Karton framework
Home-page: https://github.com/CERT-Polska/karton-misp-pusher/
License: UNKNOWN
Platform: UNKNOWN
Classifier: Programming Language :: Python
Classifier: Operating System :: OS Independent
License-File: LICENSE
Requires-Dist: karton-core (<6.0.0,>=5.0.0)
Requires-Dist: mwdb-iocextract (==1.2.2)
Requires-Dist: mwdblib (==4.4.0)
Requires-Dist: pymisp
